iwf/.openapi-python-client-config.yaml
iwf/__init__.py
iwf/client.py
iwf/client_options.py
iwf/command_request.py
iwf/command_results.py
iwf/communication.py
iwf/communication_schema.py
iwf/data_attributes.py
iwf/errors.py
iwf/iwf_api/__init__.py
iwf/iwf_api/api/__init__.py
iwf/iwf_api/api/default/__init__.py
iwf/iwf_api/api/default/get_info_healthcheck.py
iwf/iwf_api/api/default/post_api_v1_workflow_config_update.py
iwf/iwf_api/api/default/post_api_v1_workflow_dataobjects_get.py
iwf/iwf_api/api/default/post_api_v1_workflow_dataobjects_set.py
iwf/iwf_api/api/default/post_api_v1_workflow_get.py
iwf/iwf_api/api/default/post_api_v1_workflow_internal_dump.py
iwf/iwf_api/api/default/post_api_v1_workflow_reset.py
iwf/iwf_api/api/default/post_api_v1_workflow_rpc.py
iwf/iwf_api/api/default/post_api_v1_workflow_search.py
iwf/iwf_api/api/default/post_api_v1_workflow_searchattributes_get.py
iwf/iwf_api/api/default/post_api_v1_workflow_searchattributes_set.py
iwf/iwf_api/api/default/post_api_v1_workflow_signal.py
iwf/iwf_api/api/default/post_api_v1_workflow_start.py
iwf/iwf_api/api/default/post_api_v1_workflow_stop.py
iwf/iwf_api/api/default/post_api_v1_workflow_timer_skip.py
iwf/iwf_api/api/default/post_api_v_1_workflow_get_with_wait.py
iwf/iwf_api/api/default/post_api_v_1_workflow_state_decide.py
iwf/iwf_api/api/default/post_api_v_1_workflow_state_start.py
iwf/iwf_api/api/default/post_api_v_1_workflow_trigger_continue_as_new.py
iwf/iwf_api/api/default/post_api_v_1_workflow_wait_for_state_completion.py
iwf/iwf_api/api/default/post_api_v_1_workflow_worker_rpc.py
iwf/iwf_api/client.py
iwf/iwf_api/errors.py
iwf/iwf_api/models/__init__.py
iwf/iwf_api/models/channel_info.py
iwf/iwf_api/models/channel_request_status.py
iwf/iwf_api/models/command_combination.py
iwf/iwf_api/models/command_request.py
iwf/iwf_api/models/command_results.py
iwf/iwf_api/models/command_waiting_type.py
iwf/iwf_api/models/context.py
iwf/iwf_api/models/encoded_object.py
iwf/iwf_api/models/error_response.py
iwf_python_sdk-0.12.0.dist-info/LICENSE
iwf_python_sdk-0.12.0.dist-info/METADATA
iwf_python_sdk-0.12.0.dist-info/WHEEL
iwf_python_sdk-0.12.0.dist-info/RECORD
