Metadata-Version: 2.3
Name: iwf-python-sdk
Version: 0.12.0
Summary: 
Author: Indeed Engineering
Requires-Python: >=3.9,<4.0
Classifier: Programming Language :: Python :: 3
Classifier: Programming Language :: Python :: 3.9
Classifier: Programming Language :: Python :: 3.10
Classifier: Programming Language :: Python :: 3.11
Classifier: Programming Language :: Python :: 3.12
Classifier: Programming Language :: Python :: 3.13
Requires-Dist: httpx (==0.28.1)
Requires-Dist: python-dateutil (>=2.8.2,<3.0.0) ; python_version < "3.11"
